pylypenko_first_package/__init__.py
pylypenko_first_package/main.py
pylypenko_first_package-0.1.4.dist-info/METADATA
pylypenko_first_package-0.1.4.dist-info/WHEEL
pylypenko_first_package-0.1.4.dist-info/top_level.txt
pylypenko_first_package-0.1.4.dist-info/RECORD
